{
  "updated_at": "2026-05-03 15:58:14",
  "total_fetched": 24708,
  "after_prefilter": 24392,
  "unique_nodes": 13187,
  "alive_nodes": 8956,
  "country_stats": {
    "AE": 32,
    "AL": 12,
    "AM": 1,
    "AR": 2,
    "AT": 161,
    "AU": 26,
    "BE": 16,
    "BG": 6,
    "BH": 1,
    "BO": 1,
    "BR": 21,
    "BY": 5,
    "CA": 60,
    "CH": 109,
    "CL": 1,
    "CLOUDFLARE": 30,
    "CLOUDFRONT": 2,
    "CN": 7,
    "CO": 2,
    "CR": 1,
    "CY": 69,
    "CZ": 56,
    "DE": 655,
    "DK": 4,
    "EC": 2,
    "EE": 57,
    "ES": 19,
    "FASTLY": 30,
    "FI": 190,
    "FR": 257,
    "GB": 290,
    "GE": 2,
    "GOOGLE": 12,
    "GR": 8,
    "HK": 265,
    "HR": 2,
    "HU": 6,
    "ID": 8,
    "IE": 7,
    "IL": 4,
    "IN": 27,
    "IQ": 9,
    "IR": 248,
    "IT": 31,
    "JP": 245,
    "KH": 1,
    "KR": 186,
    "KZ": 42,
    "LT": 41,
    "LV": 81,
    "MA": 3,
    "MD": 40,
    "MH": 6,
    "MK": 2,
    "MN": 1,
    "MO": 1,
    "MT": 2,
    "MX": 13,
    "MY": 25,
    "NL": 595,
    "NO": 15,
    "PA": 2,
    "PE": 2,
    "PH": 2,
    "PK": 3,
    "PL": 133,
    "PR": 2,
    "PT": 1,
    "PY": 1,
    "RO": 19,
    "RU": 1603,
    "SA": 2,
    "SC": 65,
    "SE": 102,
    "SG": 159,
    "SI": 1,
    "TH": 14,
    "TR": 49,
    "TW": 47,
    "UA": 2,
    "US": 936,
    "VG": 1,
    "VN": 342,
    "ZA": 77,
    "XX": 6
  },
  "sources": [
    {
      "name": "mahdibland/V2RayAggregator",
      "count": 200,
      "status": "ok"
    },
    {
      "name": "AutoMergePublicNodes",
      "count": 68,
      "status": "ok"
    },
    {
      "name": "Barabama/nodefree",
      "count": 20,
      "status": "ok"
    },
    {
      "name": "barry-far/V2ray-Config",
      "count": 3136,
      "status": "ok"
    },
    {
      "name": "peasoft/NoMoreWalls",
      "count": 167,
      "status": "ok"
    },
    {
      "name": "Barabama/wenode",
      "count": 20,
      "status": "ok"
    },
    {
      "name": "Barabama/yudou66",
      "count": 124,
      "status": "ok"
    },
    {
      "name": "ermaozi/get_subscribe",
      "count": 26,
      "status": "ok"
    },
    {
      "name": "Barabama/v2rayshare",
      "count": 20,
      "status": "ok"
    },
    {
      "name": "mfuu/v2ray",
      "count": 67,
      "status": "ok"
    },
    {
      "name": "xyfqzy/free-nodes",
      "count": 0,
      "status": "ok"
    },
    {
      "name": "Pawdroid/sub",
      "count": 11,
      "status": "ok"
    },
    {
      "name": "proxypool/clash-meta",
      "count": 54,
      "status": "ok"
    },
    {
      "name": "yzcjd/jiedian",
      "count": 86,
      "status": "ok"
    },
    {
      "name": "Epodonios/v2ray-configs",
      "count": 4178,
      "status": "ok"
    },
    {
      "name": "MatinGhanbari/v2ray-configs",
      "count": 3997,
      "status": "ok"
    },
    {
      "name": "mianfeiclash/daily",
      "count": 129,
      "status": "ok"
    },
    {
      "name": "proxypool/clash-meta-2",
      "count": 9,
      "status": "ok"
    },
    {
      "name": "clashfree/daily",
      "count": 159,
      "status": "ok"
    },
    {
      "name": "cxddgtb/cxddzy",
      "count": 12237,
      "status": "ok"
    }
  ]
}