{
  "updated_at": "2026-04-30 16:29:58",
  "total_fetched": 26589,
  "after_prefilter": 26371,
  "unique_nodes": 14773,
  "alive_nodes": 10405,
  "country_stats": {
    "AE": 33,
    "AL": 12,
    "AM": 1,
    "AR": 3,
    "AT": 191,
    "AU": 28,
    "BE": 15,
    "BG": 8,
    "BH": 1,
    "BO": 1,
    "BR": 26,
    "BY": 7,
    "CA": 108,
    "CH": 122,
    "CL": 1,
    "CLOUDFLARE": 30,
    "CLOUDFRONT": 2,
    "CN": 35,
    "CO": 1,
    "CR": 1,
    "CY": 55,
    "CZ": 52,
    "DE": 832,
    "DK": 4,
    "EC": 14,
    "EE": 62,
    "EG": 1,
    "ES": 16,
    "FASTLY": 30,
    "FI": 224,
    "FR": 345,
    "GB": 384,
    "GE": 1,
    "GOOGLE": 17,
    "GR": 11,
    "GT": 1,
    "HK": 480,
    "HR": 2,
    "HU": 4,
    "ID": 10,
    "IE": 11,
    "IL": 7,
    "IN": 41,
    "IQ": 13,
    "IR": 183,
    "IT": 34,
    "JP": 269,
    "KH": 1,
    "KR": 387,
    "KZ": 33,
    "LT": 35,
    "LV": 109,
    "MA": 3,
    "MD": 52,
    "MH": 15,
    "MK": 2,
    "MN": 1,
    "MO": 2,
    "MT": 2,
    "MX": 24,
    "MY": 51,
    "NL": 720,
    "NO": 23,
    "PA": 2,
    "PE": 3,
    "PH": 2,
    "PK": 4,
    "PL": 138,
    "PR": 2,
    "PT": 4,
    "PY": 1,
    "RO": 24,
    "RU": 1425,
    "SA": 2,
    "SC": 52,
    "SE": 142,
    "SG": 323,
    "SI": 2,
    "TH": 14,
    "TR": 70,
    "TW": 71,
    "UA": 4,
    "US": 1141,
    "VG": 2,
    "VN": 367,
    "ZA": 105,
    "XX": 4
  },
  "sources": [
    {
      "name": "Epodonios/v2ray-configs",
      "count": 4221,
      "status": "ok"
    },
    {
      "name": "AutoMergePublicNodes",
      "count": 70,
      "status": "ok"
    },
    {
      "name": "Barabama/v2rayshare",
      "count": 28,
      "status": "ok"
    },
    {
      "name": "Barabama/nodefree",
      "count": 28,
      "status": "ok"
    },
    {
      "name": "barry-far/V2ray-Config",
      "count": 3176,
      "status": "ok"
    },
    {
      "name": "Barabama/wenode",
      "count": 28,
      "status": "ok"
    },
    {
      "name": "mfuu/v2ray",
      "count": 79,
      "status": "ok"
    },
    {
      "name": "mahdibland/V2RayAggregator",
      "count": 200,
      "status": "ok"
    },
    {
      "name": "ermaozi/get_subscribe",
      "count": 26,
      "status": "ok"
    },
    {
      "name": "peasoft/NoMoreWalls",
      "count": 214,
      "status": "ok"
    },
    {
      "name": "clashfree/daily",
      "count": 0,
      "status": "failed"
    },
    {
      "name": "MatinGhanbari/v2ray-configs",
      "count": 3997,
      "status": "ok"
    },
    {
      "name": "proxypool/clash-meta",
      "count": 54,
      "status": "ok"
    },
    {
      "name": "yzcjd/jiedian",
      "count": 86,
      "status": "ok"
    },
    {
      "name": "Barabama/yudou66",
      "count": 198,
      "status": "ok"
    },
    {
      "name": "mianfeiclash/daily",
      "count": 0,
      "status": "failed"
    },
    {
      "name": "Pawdroid/sub",
      "count": 17,
      "status": "ok"
    },
    {
      "name": "xyfqzy/free-nodes",
      "count": 0,
      "status": "ok"
    },
    {
      "name": "proxypool/clash-meta-2",
      "count": 67,
      "status": "ok"
    },
    {
      "name": "cxddgtb/cxddzy",
      "count": 14100,
      "status": "ok"
    }
  ]
}