{
  "updated_at": "2026-06-13 21:24:57",
  "total_fetched": 30899,
  "after_prefilter": 30558,
  "unique_nodes": 16654,
  "alive_nodes": 11656,
  "country_stats": {
    "AE": 52,
    "AL": 17,
    "AM": 9,
    "AQ": 4,
    "AR": 1,
    "AT": 101,
    "AU": 36,
    "BD": 4,
    "BE": 27,
    "BG": 12,
    "BR": 5,
    "BY": 15,
    "CA": 89,
    "CH": 88,
    "CL": 5,
    "CLOUDFLARE": 30,
    "CLOUDFRONT": 11,
    "CN": 2,
    "CO": 1,
    "CY": 45,
    "CZ": 75,
    "DE": 1150,
    "DK": 9,
    "DO": 7,
    "EE": 59,
    "ES": 26,
    "FASTLY": 30,
    "FI": 240,
    "FR": 558,
    "GB": 316,
    "GE": 5,
    "GI": 2,
    "GOOGLE": 20,
    "GR": 21,
    "GT": 1,
    "HK": 261,
    "HR": 1,
    "HU": 17,
    "ID": 9,
    "IE": 19,
    "IL": 24,
    "IN": 12,
    "IQ": 4,
    "IR": 388,
    "IS": 7,
    "IT": 87,
    "JP": 240,
    "KH": 1,
    "KR": 213,
    "KZ": 57,
    "LT": 56,
    "LV": 123,
    "MA": 1,
    "MD": 30,
    "MH": 27,
    "MK": 1,
    "MN": 1,
    "MO": 1,
    "MX": 6,
    "MY": 30,
    "NL": 844,
    "NO": 8,
    "NZ": 5,
    "PE": 1,
    "PH": 3,
    "PL": 202,
    "RO": 89,
    "RS": 1,
    "RU": 1666,
    "SA": 5,
    "SC": 140,
    "SE": 156,
    "SG": 285,
    "SK": 1,
    "TH": 15,
    "TR": 90,
    "TW": 79,
    "UA": 8,
    "US": 1616,
    "VN": 15,
    "ZA": 19,
    "XX": 11
  },
  "sources": [
    {
      "name": "mahdibland/V2RayAggregator",
      "count": 200,
      "status": "ok"
    },
    {
      "name": "AutoMergePublicNodes",
      "count": 48,
      "status": "ok"
    },
    {
      "name": "Barabama/nodefree",
      "count": 23,
      "status": "ok"
    },
    {
      "name": "Barabama/wenode",
      "count": 23,
      "status": "ok"
    },
    {
      "name": "Barabama/v2rayshare",
      "count": 23,
      "status": "ok"
    },
    {
      "name": "MatinGhanbari/v2ray-configs",
      "count": 3997,
      "status": "ok"
    },
    {
      "name": "peasoft/NoMoreWalls",
      "count": 93,
      "status": "ok"
    },
    {
      "name": "Epodonios/v2ray-configs",
      "count": 5864,
      "status": "ok"
    },
    {
      "name": "Barabama/yudou66",
      "count": 166,
      "status": "ok"
    },
    {
      "name": "mfuu/v2ray",
      "count": 245,
      "status": "ok"
    },
    {
      "name": "ermaozi/get_subscribe",
      "count": 29,
      "status": "ok"
    },
    {
      "name": "barry-far/V2ray-Config",
      "count": 5185,
      "status": "ok"
    },
    {
      "name": "yzcjd/jiedian",
      "count": 86,
      "status": "ok"
    },
    {
      "name": "xyfqzy/free-nodes",
      "count": 0,
      "status": "ok"
    },
    {
      "name": "Pawdroid/sub",
      "count": 8,
      "status": "ok"
    },
    {
      "name": "proxypool/clash-meta",
      "count": 9,
      "status": "ok"
    },
    {
      "name": "proxypool/clash-meta-2",
      "count": 1,
      "status": "ok"
    },
    {
      "name": "mianfeiclash/daily",
      "count": 241,
      "status": "ok"
    },
    {
      "name": "clashfree/daily",
      "count": 198,
      "status": "ok"
    },
    {
      "name": "cxddgtb/cxddzy",
      "count": 14460,
      "status": "ok"
    }
  ]
}