{
  "updated_at": "2026-05-19 21:29:27",
  "total_fetched": 27543,
  "after_prefilter": 27218,
  "unique_nodes": 16088,
  "alive_nodes": 11418,
  "country_stats": {
    "AE": 42,
    "AL": 14,
    "AM": 2,
    "AQ": 2,
    "AR": 1,
    "AT": 195,
    "AU": 32,
    "BE": 15,
    "BG": 5,
    "BH": 1,
    "BO": 1,
    "BR": 19,
    "BY": 3,
    "CA": 79,
    "CH": 46,
    "CLOUDFLARE": 30,
    "CLOUDFRONT": 3,
    "CO": 1,
    "CY": 53,
    "CZ": 55,
    "DE": 964,
    "DK": 5,
    "EC": 2,
    "EE": 56,
    "EG": 1,
    "ES": 27,
    "FASTLY": 30,
    "FI": 200,
    "FR": 391,
    "GB": 364,
    "GE": 1,
    "GOOGLE": 18,
    "GR": 16,
    "GT": 1,
    "HK": 286,
    "HR": 2,
    "HU": 8,
    "ID": 4,
    "IE": 10,
    "IL": 14,
    "IN": 24,
    "IQ": 8,
    "IR": 400,
    "IT": 40,
    "JP": 425,
    "KH": 1,
    "KR": 335,
    "KZ": 48,
    "LT": 44,
    "LV": 117,
    "MA": 3,
    "MD": 35,
    "MH": 11,
    "MK": 2,
    "MN": 1,
    "MO": 1,
    "MT": 2,
    "MX": 18,
    "MY": 39,
    "NG": 1,
    "NL": 796,
    "NO": 15,
    "PA": 2,
    "PE": 2,
    "PH": 2,
    "PK": 2,
    "PL": 141,
    "PR": 1,
    "PT": 3,
    "PY": 1,
    "RO": 20,
    "RU": 1843,
    "SA": 2,
    "SC": 95,
    "SE": 170,
    "SG": 259,
    "SI": 1,
    "TH": 16,
    "TR": 43,
    "TW": 60,
    "UA": 4,
    "US": 1600,
    "VN": 363,
    "ZA": 75,
    "XX": 4
  },
  "sources": [
    {
      "name": "barry-far/V2ray-Config",
      "count": 3310,
      "status": "ok"
    },
    {
      "name": "AutoMergePublicNodes",
      "count": 47,
      "status": "ok"
    },
    {
      "name": "Barabama/nodefree",
      "count": 23,
      "status": "ok"
    },
    {
      "name": "Barabama/v2rayshare",
      "count": 23,
      "status": "ok"
    },
    {
      "name": "mahdibland/V2RayAggregator",
      "count": 200,
      "status": "ok"
    },
    {
      "name": "Barabama/wenode",
      "count": 23,
      "status": "ok"
    },
    {
      "name": "Epodonios/v2ray-configs",
      "count": 4370,
      "status": "ok"
    },
    {
      "name": "ermaozi/get_subscribe",
      "count": 26,
      "status": "ok"
    },
    {
      "name": "Barabama/yudou66",
      "count": 166,
      "status": "ok"
    },
    {
      "name": "mfuu/v2ray",
      "count": 64,
      "status": "ok"
    },
    {
      "name": "peasoft/NoMoreWalls",
      "count": 188,
      "status": "ok"
    },
    {
      "name": "xyfqzy/free-nodes",
      "count": 0,
      "status": "ok"
    },
    {
      "name": "MatinGhanbari/v2ray-configs",
      "count": 3998,
      "status": "ok"
    },
    {
      "name": "Pawdroid/sub",
      "count": 14,
      "status": "ok"
    },
    {
      "name": "proxypool/clash-meta",
      "count": 44,
      "status": "ok"
    },
    {
      "name": "yzcjd/jiedian",
      "count": 86,
      "status": "ok"
    },
    {
      "name": "mianfeiclash/daily",
      "count": 153,
      "status": "ok"
    },
    {
      "name": "proxypool/clash-meta-2",
      "count": 58,
      "status": "ok"
    },
    {
      "name": "clashfree/daily",
      "count": 0,
      "status": "ok"
    },
    {
      "name": "cxddgtb/cxddzy",
      "count": 14750,
      "status": "ok"
    }
  ]
}