{
  "updated_at": "2026-06-07 21:21:52",
  "total_fetched": 28339,
  "after_prefilter": 28056,
  "unique_nodes": 14882,
  "alive_nodes": 9672,
  "country_stats": {
    "AE": 37,
    "AL": 17,
    "AM": 11,
    "AR": 1,
    "AT": 85,
    "AU": 25,
    "BD": 2,
    "BE": 22,
    "BG": 13,
    "BR": 5,
    "BY": 13,
    "CA": 65,
    "CH": 71,
    "CL": 1,
    "CLOUDFLARE": 30,
    "CLOUDFRONT": 7,
    "CN": 1,
    "CY": 26,
    "CZ": 57,
    "DE": 915,
    "DK": 6,
    "EE": 45,
    "ES": 16,
    "FASTLY": 30,
    "FI": 328,
    "FR": 534,
    "GB": 246,
    "GE": 3,
    "GOOGLE": 13,
    "GR": 21,
    "GT": 1,
    "HK": 168,
    "HU": 6,
    "ID": 11,
    "IE": 16,
    "IL": 14,
    "IN": 10,
    "IQ": 4,
    "IR": 359,
    "IS": 2,
    "IT": 76,
    "JP": 199,
    "KR": 182,
    "KZ": 38,
    "LT": 39,
    "LV": 97,
    "MA": 1,
    "MD": 19,
    "MH": 18,
    "MN": 1,
    "MO": 1,
    "MX": 3,
    "MY": 17,
    "NL": 621,
    "NO": 8,
    "NZ": 5,
    "PH": 1,
    "PL": 168,
    "RO": 50,
    "RU": 1465,
    "SA": 4,
    "SC": 78,
    "SE": 117,
    "SG": 174,
    "TH": 6,
    "TR": 62,
    "TW": 71,
    "UA": 6,
    "US": 1188,
    "VN": 10,
    "ZA": 15,
    "XX": 4
  },
  "sources": [
    {
      "name": "AutoMergePublicNodes",
      "count": 63,
      "status": "ok"
    },
    {
      "name": "barry-far/V2ray-Config",
      "count": 5034,
      "status": "ok"
    },
    {
      "name": "Barabama/v2rayshare",
      "count": 23,
      "status": "ok"
    },
    {
      "name": "Barabama/wenode",
      "count": 23,
      "status": "ok"
    },
    {
      "name": "Barabama/nodefree",
      "count": 23,
      "status": "ok"
    },
    {
      "name": "mahdibland/V2RayAggregator",
      "count": 200,
      "status": "ok"
    },
    {
      "name": "MatinGhanbari/v2ray-configs",
      "count": 3999,
      "status": "ok"
    },
    {
      "name": "Epodonios/v2ray-configs",
      "count": 5811,
      "status": "ok"
    },
    {
      "name": "Barabama/yudou66",
      "count": 166,
      "status": "ok"
    },
    {
      "name": "ermaozi/get_subscribe",
      "count": 29,
      "status": "ok"
    },
    {
      "name": "mfuu/v2ray",
      "count": 77,
      "status": "ok"
    },
    {
      "name": "peasoft/NoMoreWalls",
      "count": 113,
      "status": "ok"
    },
    {
      "name": "yzcjd/jiedian",
      "count": 86,
      "status": "ok"
    },
    {
      "name": "Pawdroid/sub",
      "count": 8,
      "status": "ok"
    },
    {
      "name": "xyfqzy/free-nodes",
      "count": 0,
      "status": "ok"
    },
    {
      "name": "proxypool/clash-meta",
      "count": 16,
      "status": "ok"
    },
    {
      "name": "proxypool/clash-meta-2",
      "count": 3,
      "status": "ok"
    },
    {
      "name": "mianfeiclash/daily",
      "count": 193,
      "status": "ok"
    },
    {
      "name": "clashfree/daily",
      "count": 188,
      "status": "ok"
    },
    {
      "name": "cxddgtb/cxddzy",
      "count": 12284,
      "status": "ok"
    }
  ]
}